CHANGES.txt
README.txt
setup.py
collective/__init__.py
collective.dtwidget.egg-info/PKG-INFO
collective.dtwidget.egg-info/SOURCES.txt
collective.dtwidget.egg-info/dependency_links.txt
collective.dtwidget.egg-info/namespace_packages.txt
collective.dtwidget.egg-info/not-zip-safe
collective.dtwidget.egg-info/requires.txt
collective.dtwidget.egg-info/top_level.txt
collective/dtwidget/__init__.py
collective/dtwidget/dtwidget.pt
collective/dtwidget/dtwidget.py
collective/dtwidget/overrides.zcml
docs/LICENSE.GPL
docs/LICENSE.txt