Metadata-Version: 1.0
Name: collective.dtwidget
Version: 0.3
Summary: Munges the ATDateTime CalendarWidget into a formlib widget.  Plone only
Home-page: http://pypi.python.org/pypi/collective.dtwidget
Author: Matthew Wilkes
Author-email: matthew.wilkes@circulartriangle.eu
License: GPL
Keywords: formlib widget Datetime
Platform: UNKNOWN
Classifier: Framework :: Plone
Classifier: Framework :: Zope2
Classifier: Programming Language :: Python
